rfhotjup/__init__.py
rfhotjup/rfhotjup.py
rfhotjup/database/predicted_radio_fluxes.db
rfhotjup-1.0.1.dist-info/METADATA
rfhotjup-1.0.1.dist-info/WHEEL
rfhotjup-1.0.1.dist-info/top_level.txt
rfhotjup-1.0.1.dist-info/RECORD
